{
  "slug": "somerset-house-s-decentralise",
  "title": "Somerset House’s Decentralise",
  "liveUrl": "https://www.somersethouse.org.uk/blog/decentralise",
  "domain": "www.somersethouse.org.uk",
  "loadmoreUrl": "https://loadmo.re/posts/somerset-house-s-decentralise",
  "sourceLabel": "loadmo.re",
  "sourceUrl": "https://loadmo.re/posts/somerset-house-s-decentralise",
  "description": "'Decentralise' is an online platform which explore the history of Black British art, through engaging with 16 key objects from Somerset House exhibition.",
  "credits": "COMUZI, DxR Zone & Somerset House",
  "added": "",
  "tags": [
    "tactile",
    "illustration",
    "sound-design"
  ],
  "posterImage": "https://loadmo.re/media/pages/posts/somerset-house-s-decentralise/8cb04b7ece-1648669380/0289_somersethouses-decentralise-home-cover-min.jpg",
  "previewVideo": "https://loadmo.re/media/pages/posts/somerset-house-s-decentralise/24f131ed3a-1648669399/0289_somersethouses-decentralise-post-min.mp4",
  "captureChecklist": {
    "loadmoreMetadataParsed": true,
    "desktopVisited": true,
    "mobileVisited": true,
    "desktopScreenshotSaved": true,
    "mobileScreenshotSaved": true,
    "fontsExtracted": true,
    "colorPaletteExtracted": true
  },
  "capture": {
    "status": "ok",
    "capturedAt": "2026-04-06T20:27:24.910Z",
    "desktop": {
      "ok": true,
      "analysis": {
        "mode": "desktop",
        "title": "Somerset House | 404",
        "url": "https://www.somersethouse.org.uk/blog/decentralise",
        "body": {
          "backgroundColor": "rgba(0, 0, 0, 0)",
          "color": "rgb(0, 0, 0)",
          "fontFamily": "Grotesk, ui-sans-serif, system-ui, sans-serif, \"Apple Color Emoji\", \"Segoe UI Emoji\", \"Segoe UI Symbol\", \"Noto Color Emoji\"",
          "fontSize": "16px",
          "lineHeight": "24px"
        },
        "heading": {
          "tag": "h1",
          "text": "404",
          "color": "rgb(0, 0, 0)",
          "backgroundColor": "rgba(0, 0, 0, 0)",
          "fontFamily": "Grotesk, ui-sans-serif, system-ui, sans-serif, \"Apple Color Emoji\", \"Segoe UI Emoji\", \"Segoe UI Symbol\", \"Noto Color Emoji\"",
          "fontSize": "30px",
          "fontWeight": "400",
          "borderRadius": "0px",
          "boxShadow": "none",
          "letterSpacing": "2%",
          "lineHeight": "42px",
          "display": "block",
          "position": "static"
        },
        "bodyText": {
          "tag": "p",
          "text": "Page not found.",
          "color": "rgb(0, 0, 0)",
          "backgroundColor": "rgba(0, 0, 0, 0)",
          "fontFamily": "Grotesk, ui-sans-serif, system-ui, sans-serif, \"Apple Color Emoji\", \"Segoe UI Emoji\", \"Segoe UI Symbol\", \"Noto Color Emoji\"",
          "fontSize": "14px",
          "fontWeight": "400",
          "borderRadius": "0px",
          "boxShadow": "none",
          "letterSpacing": "2%",
          "lineHeight": "19.6px",
          "display": "block",
          "position": "static"
        },
        "button": {
          "tag": "button",
          "text": "Favourited",
          "color": "rgb(0, 0, 0)",
          "backgroundColor": "rgb(255, 255, 255)",
          "fontFamily": "Grotesk, ui-sans-serif, system-ui, sans-serif, \"Apple Color Emoji\", \"Segoe UI Emoji\", \"Segoe UI Symbol\", \"Noto Color Emoji\"",
          "fontSize": "14px",
          "fontWeight": "400",
          "borderRadius": "28px",
          "boxShadow": "none",
          "letterSpacing": "2%",
          "lineHeight": "19.6px",
          "display": "flex",
          "position": "static"
        },
        "link": {
          "tag": "a",
          "text": "Skip to main content",
          "color": "rgb(0, 0, 0)",
          "backgroundColor": "rgb(255, 255, 255)",
          "fontFamily": "Grotesk, ui-sans-serif, system-ui, sans-serif, \"Apple Color Emoji\", \"Segoe UI Emoji\", \"Segoe UI Symbol\", \"Noto Color Emoji\"",
          "fontSize": "16px",
          "fontWeight": "400",
          "borderRadius": "0px",
          "boxShadow": "none",
          "letterSpacing": "normal",
          "lineHeight": "24px",
          "display": "block",
          "position": "absolute"
        },
        "sticky": false,
        "fonts": [
          {
            "family": "Grotesk",
            "style": "normal",
            "weight": "400",
            "status": "loaded"
          },
          {
            "family": "Roman",
            "style": "normal",
            "weight": "400",
            "status": "unloaded"
          },
          {
            "family": "hotjar",
            "style": "normal",
            "weight": "normal",
            "status": "unloaded"
          },
          {
            "family": "roboto",
            "style": "normal",
            "weight": "400",
            "status": "loaded"
          },
          {
            "family": "roboto",
            "style": "normal",
            "weight": "500",
            "status": "loaded"
          }
        ],
        "sample": [
          {
            "tag": "body",
            "text": "Skip to main contentSkip to primary navigationSkip to secondary navigationMenuMenuCloseHomeWhat's OnExhibitionsEventsOnl",
            "color": "rgb(0, 0, 0)",
            "backgroundColor": "rgba(0, 0, 0, 0)",
            "fontFamily": "Grotesk, ui-sans-serif, system-ui, sans-serif, \"Apple Color Emoji\", \"Segoe UI Emoji\", \"Segoe UI Symbol\", \"Noto Color Emoji\"",
            "fontSize": "16px",
            "fontWeight": "400",
            "borderRadius": "0px",
            "boxShadow": "none",
            "letterSpacing": "normal",
            "lineHeight": "24px",
            "display": "block",
            "position": "static"
          },
          {
            "tag": "a",
            "text": "Skip to main content",
            "color": "rgb(0, 0, 0)",
            "backgroundColor": "rgb(255, 255, 255)",
            "fontFamily": "Grotesk, ui-sans-serif, system-ui, sans-serif, \"Apple Color Emoji\", \"Segoe UI Emoji\", \"Segoe UI Symbol\", \"Noto Color Emoji\"",
            "fontSize": "16px",
            "fontWeight": "400",
            "borderRadius": "0px",
            "boxShadow": "none",
            "letterSpacing": "normal",
            "lineHeight": "24px",
            "display": "block",
            "position": "absolute"
          },
          {
            "tag": "a",
            "text": "Skip to primary navigation",
            "color": "rgb(0, 0, 0)",
            "backgroundColor": "rgb(255, 255, 255)",
            "fontFamily": "Grotesk, ui-sans-serif, system-ui, sans-serif, \"Apple Color Emoji\", \"Segoe UI Emoji\", \"Segoe UI Symbol\", \"Noto Color Emoji\"",
            "fontSize": "16px",
            "fontWeight": "400",
            "borderRadius": "0px",
            "boxShadow": "none",
            "letterSpacing": "normal",
            "lineHeight": "24px",
            "display": "block",
            "position": "absolute"
          },
          {
            "tag": "a",
            "text": "Skip to secondary navigation",
            "color": "rgb(0, 0, 0)",
            "backgroundColor": "rgb(255, 255, 255)",
            "fontFamily": "Grotesk, ui-sans-serif, system-ui, sans-serif, \"Apple Color Emoji\", \"Segoe UI Emoji\", \"Segoe UI Symbol\", \"Noto Color Emoji\"",
            "fontSize": "16px",
            "fontWeight": "400",
            "borderRadius": "0px",
            "boxShadow": "none",
            "letterSpacing": "normal",
            "lineHeight": "24px",
            "display": "block",
            "position": "absolute"
          },
          {
            "tag": "button",
            "text": "Favourited",
            "color": "rgb(0, 0, 0)",
            "backgroundColor": "rgb(255, 255, 255)",
            "fontFamily": "Grotesk, ui-sans-serif, system-ui, sans-serif, \"Apple Color Emoji\", \"Segoe UI Emoji\", \"Segoe UI Symbol\", \"Noto Color Emoji\"",
            "fontSize": "14px",
            "fontWeight": "400",
            "borderRadius": "28px",
            "boxShadow": "none",
            "letterSpacing": "2%",
            "lineHeight": "19.6px",
            "display": "flex",
            "position": "static"
          },
          {
            "tag": "button",
            "text": "Search",
            "color": "rgb(0, 0, 0)",
            "backgroundColor": "rgb(255, 255, 255)",
            "fontFamily": "Grotesk, ui-sans-serif, system-ui, sans-serif, \"Apple Color Emoji\", \"Segoe UI Emoji\", \"Segoe UI Symbol\", \"Noto Color Emoji\"",
            "fontSize": "14px",
            "fontWeight": "400",
            "borderRadius": "28px",
            "boxShadow": "none",
            "letterSpacing": "2%",
            "lineHeight": "19.6px",
            "display": "flex",
            "position": "static"
          },
          {
            "tag": "nav",
            "text": "MenuHomeWhat's OnExhibitionsEventsOnline CommissionsSomerset House StudiosArtistsResidencies and OpportunitiesCreative W",
            "color": "lch(0 0 0)",
            "backgroundColor": "rgba(0, 0, 0, 0)",
            "fontFamily": "Grotesk, ui-sans-serif, system-ui, sans-serif, \"Apple Color Emoji\", \"Segoe UI Emoji\", \"Segoe UI Symbol\", \"Noto Color Emoji\"",
            "fontSize": "16px",
            "fontWeight": "400",
            "borderRadius": "0px",
            "boxShadow": "none",
            "letterSpacing": "normal",
            "lineHeight": "24px",
            "display": "block",
            "position": "static"
          },
          {
            "tag": "a",
            "text": "",
            "color": "lch(0 0 0)",
            "backgroundColor": "rgba(0, 0, 0, 0)",
            "fontFamily": "Grotesk, ui-sans-serif, system-ui, sans-serif, \"Apple Color Emoji\", \"Segoe UI Emoji\", \"Segoe UI Symbol\", \"Noto Color Emoji\"",
            "fontSize": "16px",
            "fontWeight": "400",
            "borderRadius": "0px",
            "boxShadow": "none",
            "letterSpacing": "normal",
            "lineHeight": "24px",
            "display": "block",
            "position": "static"
          },
          {
            "tag": "button",
            "text": "Menu",
            "color": "lch(0 0 0)",
            "backgroundColor": "rgba(0, 0, 0, 0)",
            "fontFamily": "Grotesk, ui-sans-serif, system-ui, sans-serif, \"Apple Color Emoji\", \"Segoe UI Emoji\", \"Segoe UI Symbol\", \"Noto Color Emoji\"",
            "fontSize": "16px",
            "fontWeight": "400",
            "borderRadius": "0px",
            "boxShadow": "none",
            "letterSpacing": "normal",
            "lineHeight": "24px",
            "display": "inline-block",
            "position": "static"
          },
          {
            "tag": "a",
            "text": "Home",
            "color": "lch(0 0 0)",
            "backgroundColor": "rgba(0, 0, 0, 0)",
            "fontFamily": "Grotesk, ui-sans-serif, system-ui, sans-serif, \"Apple Color Emoji\", \"Segoe UI Emoji\", \"Segoe UI Symbol\", \"Noto Color Emoji\"",
            "fontSize": "17px",
            "fontWeight": "400",
            "borderRadius": "0px",
            "boxShadow": "none",
            "letterSpacing": "2%",
            "lineHeight": "25.5px",
            "display": "inline",
            "position": "static"
          },
          {
            "tag": "main",
            "text": "404Page not found.Home of Cultural InnovatorsOpening HoursStrand entrance8am—11pmThe Courtauld Gallery10am—6pmNew Wing8a",
            "color": "rgb(0, 0, 0)",
            "backgroundColor": "rgba(0, 0, 0, 0)",
            "fontFamily": "Grotesk, ui-sans-serif, system-ui, sans-serif, \"Apple Color Emoji\", \"Segoe UI Emoji\", \"Segoe UI Symbol\", \"Noto Color Emoji\"",
            "fontSize": "16px",
            "fontWeight": "400",
            "borderRadius": "0px",
            "boxShadow": "none",
            "letterSpacing": "normal",
            "lineHeight": "24px",
            "display": "block",
            "position": "static"
          },
          {
            "tag": "header",
            "text": "404Page not found.",
            "color": "rgb(0, 0, 0)",
            "backgroundColor": "rgb(255, 255, 255)",
            "fontFamily": "Grotesk, ui-sans-serif, system-ui, sans-serif, \"Apple Color Emoji\", \"Segoe UI Emoji\", \"Segoe UI Symbol\", \"Noto Color Emoji\"",
            "fontSize": "16px",
            "fontWeight": "400",
            "borderRadius": "7px",
            "boxShadow": "none",
            "letterSpacing": "normal",
            "lineHeight": "24px",
            "display": "block",
            "position": "static"
          },
          {
            "tag": "h1",
            "text": "404",
            "color": "rgb(0, 0, 0)",
            "backgroundColor": "rgba(0, 0, 0, 0)",
            "fontFamily": "Grotesk, ui-sans-serif, system-ui, sans-serif, \"Apple Color Emoji\", \"Segoe UI Emoji\", \"Segoe UI Symbol\", \"Noto Color Emoji\"",
            "fontSize": "30px",
            "fontWeight": "400",
            "borderRadius": "0px",
            "boxShadow": "none",
            "letterSpacing": "2%",
            "lineHeight": "42px",
            "display": "block",
            "position": "static"
          },
          {
            "tag": "p",
            "text": "Page not found.",
            "color": "rgb(0, 0, 0)",
            "backgroundColor": "rgba(0, 0, 0, 0)",
            "fontFamily": "Grotesk, ui-sans-serif, system-ui, sans-serif, \"Apple Color Emoji\", \"Segoe UI Emoji\", \"Segoe UI Symbol\", \"Noto Color Emoji\"",
            "fontSize": "14px",
            "fontWeight": "400",
            "borderRadius": "0px",
            "boxShadow": "none",
            "letterSpacing": "2%",
            "lineHeight": "19.6px",
            "display": "block",
            "position": "static"
          },
          {
            "tag": "footer",
            "text": "Home of Cultural InnovatorsOpening HoursStrand entrance8am—11pmThe Courtauld Gallery10am—6pmNew Wing8am—11pmAboutAbout U",
            "color": "lch(0 0 0)",
            "backgroundColor": "rgb(255, 255, 255)",
            "fontFamily": "Grotesk, ui-sans-serif, system-ui, sans-serif, \"Apple Color Emoji\", \"Segoe UI Emoji\", \"Segoe UI Symbol\", \"Noto Color Emoji\"",
            "fontSize": "16px",
            "fontWeight": "400",
            "borderRadius": "7px",
            "boxShadow": "none",
            "letterSpacing": "normal",
            "lineHeight": "24px",
            "display": "block",
            "position": "static"
          },
          {
            "tag": "h2",
            "text": "Home of Cultural Innovators",
            "color": "lch(0 0 0)",
            "backgroundColor": "rgba(0, 0, 0, 0)",
            "fontFamily": "Grotesk, ui-sans-serif, system-ui, sans-serif, \"Apple Color Emoji\", \"Segoe UI Emoji\", \"Segoe UI Symbol\", \"Noto Color Emoji\"",
            "fontSize": "30px",
            "fontWeight": "400",
            "borderRadius": "0px",
            "boxShadow": "none",
            "letterSpacing": "2%",
            "lineHeight": "42px",
            "display": "block",
            "position": "static"
          },
          {
            "tag": "h3",
            "text": "Opening Hours",
            "color": "lch(0 0 0)",
            "backgroundColor": "rgba(0, 0, 0, 0)",
            "fontFamily": "Grotesk, ui-sans-serif, system-ui, sans-serif, \"Apple Color Emoji\", \"Segoe UI Emoji\", \"Segoe UI Symbol\", \"Noto Color Emoji\"",
            "fontSize": "14px",
            "fontWeight": "400",
            "borderRadius": "0px",
            "boxShadow": "none",
            "letterSpacing": "2%",
            "lineHeight": "19.6px",
            "display": "block",
            "position": "static"
          },
          {
            "tag": "nav",
            "text": "AboutAbout UsContact UsOur TeamSupport UsVenue HireShopCareersPressPrivacy PolicyCookie PolicyCustomer Feedback and Comp",
            "color": "lch(0 0 0)",
            "backgroundColor": "rgba(0, 0, 0, 0)",
            "fontFamily": "Grotesk, ui-sans-serif, system-ui, sans-serif, \"Apple Color Emoji\", \"Segoe UI Emoji\", \"Segoe UI Symbol\", \"Noto Color Emoji\"",
            "fontSize": "14px",
            "fontWeight": "400",
            "borderRadius": "0px",
            "boxShadow": "none",
            "letterSpacing": "2%",
            "lineHeight": "19.6px",
            "display": "grid",
            "position": "static"
          },
          {
            "tag": "h3",
            "text": "About",
            "color": "lch(0 0 0)",
            "backgroundColor": "rgba(0, 0, 0, 0)",
            "fontFamily": "Grotesk, ui-sans-serif, system-ui, sans-serif, \"Apple Color Emoji\", \"Segoe UI Emoji\", \"Segoe UI Symbol\", \"Noto Color Emoji\"",
            "fontSize": "14px",
            "fontWeight": "400",
            "borderRadius": "0px",
            "boxShadow": "none",
            "letterSpacing": "2%",
            "lineHeight": "19.6px",
            "display": "block",
            "position": "static"
          },
          {
            "tag": "p",
            "text": "About Us",
            "color": "lch(0 0 0)",
            "backgroundColor": "rgba(0, 0, 0, 0)",
            "fontFamily": "Grotesk, ui-sans-serif, system-ui, sans-serif, \"Apple Color Emoji\", \"Segoe UI Emoji\", \"Segoe UI Symbol\", \"Noto Color Emoji\"",
            "fontSize": "14px",
            "fontWeight": "400",
            "borderRadius": "0px",
            "boxShadow": "none",
            "letterSpacing": "2%",
            "lineHeight": "19.6px",
            "display": "block",
            "position": "static"
          },
          {
            "tag": "a",
            "text": "About Us",
            "color": "lch(0 0 0)",
            "backgroundColor": "rgba(0, 0, 0, 0)",
            "fontFamily": "Grotesk, ui-sans-serif, system-ui, sans-serif, \"Apple Color Emoji\", \"Segoe UI Emoji\", \"Segoe UI Symbol\", \"Noto Color Emoji\"",
            "fontSize": "14px",
            "fontWeight": "400",
            "borderRadius": "0px",
            "boxShadow": "none",
            "letterSpacing": "2%",
            "lineHeight": "19.6px",
            "display": "inline",
            "position": "static"
          },
          {
            "tag": "p",
            "text": "Contact Us",
            "color": "lch(0 0 0)",
            "backgroundColor": "rgba(0, 0, 0, 0)",
            "fontFamily": "Grotesk, ui-sans-serif, system-ui, sans-serif, \"Apple Color Emoji\", \"Segoe UI Emoji\", \"Segoe UI Symbol\", \"Noto Color Emoji\"",
            "fontSize": "14px",
            "fontWeight": "400",
            "borderRadius": "0px",
            "boxShadow": "none",
            "letterSpacing": "2%",
            "lineHeight": "19.6px",
            "display": "block",
            "position": "static"
          },
          {
            "tag": "a",
            "text": "Contact Us",
            "color": "lch(0 0 0)",
            "backgroundColor": "rgba(0, 0, 0, 0)",
            "fontFamily": "Grotesk, ui-sans-serif, system-ui, sans-serif, \"Apple Color Emoji\", \"Segoe UI Emoji\", \"Segoe UI Symbol\", \"Noto Color Emoji\"",
            "fontSize": "14px",
            "fontWeight": "400",
            "borderRadius": "0px",
            "boxShadow": "none",
            "letterSpacing": "2%",
            "lineHeight": "19.6px",
            "display": "inline",
            "position": "static"
          },
          {
            "tag": "p",
            "text": "Our Team",
            "color": "lch(0 0 0)",
            "backgroundColor": "rgba(0, 0, 0, 0)",
            "fontFamily": "Grotesk, ui-sans-serif, system-ui, sans-serif, \"Apple Color Emoji\", \"Segoe UI Emoji\", \"Segoe UI Symbol\", \"Noto Color Emoji\"",
            "fontSize": "14px",
            "fontWeight": "400",
            "borderRadius": "0px",
            "boxShadow": "none",
            "letterSpacing": "2%",
            "lineHeight": "19.6px",
            "display": "block",
            "position": "static"
          },
          {
            "tag": "a",
            "text": "Our Team",
            "color": "lch(0 0 0)",
            "backgroundColor": "rgba(0, 0, 0, 0)",
            "fontFamily": "Grotesk, ui-sans-serif, system-ui, sans-serif, \"Apple Color Emoji\", \"Segoe UI Emoji\", \"Segoe UI Symbol\", \"Noto Color Emoji\"",
            "fontSize": "14px",
            "fontWeight": "400",
            "borderRadius": "0px",
            "boxShadow": "none",
            "letterSpacing": "2%",
            "lineHeight": "19.6px",
            "display": "inline",
            "position": "static"
          },
          {
            "tag": "p",
            "text": "Support Us",
            "color": "lch(0 0 0)",
            "backgroundColor": "rgba(0, 0, 0, 0)",
            "fontFamily": "Grotesk, ui-sans-serif, system-ui, sans-serif, \"Apple Color Emoji\", \"Segoe UI Emoji\", \"Segoe UI Symbol\", \"Noto Color Emoji\"",
            "fontSize": "14px",
            "fontWeight": "400",
            "borderRadius": "0px",
            "boxShadow": "none",
            "letterSpacing": "2%",
            "lineHeight": "19.6px",
            "display": "block",
            "position": "static"
          },
          {
            "tag": "a",
            "text": "Support Us",
            "color": "lch(0 0 0)",
            "backgroundColor": "rgba(0, 0, 0, 0)",
            "fontFamily": "Grotesk, ui-sans-serif, system-ui, sans-serif, \"Apple Color Emoji\", \"Segoe UI Emoji\", \"Segoe UI Symbol\", \"Noto Color Emoji\"",
            "fontSize": "14px",
            "fontWeight": "400",
            "borderRadius": "0px",
            "boxShadow": "none",
            "letterSpacing": "2%",
            "lineHeight": "19.6px",
            "display": "inline",
            "position": "static"
          },
          {
            "tag": "p",
            "text": "Venue Hire",
            "color": "lch(0 0 0)",
            "backgroundColor": "rgba(0, 0, 0, 0)",
            "fontFamily": "Grotesk, ui-sans-serif, system-ui, sans-serif, \"Apple Color Emoji\", \"Segoe UI Emoji\", \"Segoe UI Symbol\", \"Noto Color Emoji\"",
            "fontSize": "14px",
            "fontWeight": "400",
            "borderRadius": "0px",
            "boxShadow": "none",
            "letterSpacing": "2%",
            "lineHeight": "19.6px",
            "display": "block",
            "position": "static"
          },
          {
            "tag": "a",
            "text": "Venue Hire",
            "color": "lch(0 0 0)",
            "backgroundColor": "rgba(0, 0, 0, 0)",
            "fontFamily": "Grotesk, ui-sans-serif, system-ui, sans-serif, \"Apple Color Emoji\", \"Segoe UI Emoji\", \"Segoe UI Symbol\", \"Noto Color Emoji\"",
            "fontSize": "14px",
            "fontWeight": "400",
            "borderRadius": "0px",
            "boxShadow": "none",
            "letterSpacing": "2%",
            "lineHeight": "19.6px",
            "display": "inline",
            "position": "static"
          },
          {
            "tag": "p",
            "text": "Shop",
            "color": "lch(0 0 0)",
            "backgroundColor": "rgba(0, 0, 0, 0)",
            "fontFamily": "Grotesk, ui-sans-serif, system-ui, sans-serif, \"Apple Color Emoji\", \"Segoe UI Emoji\", \"Segoe UI Symbol\", \"Noto Color Emoji\"",
            "fontSize": "14px",
            "fontWeight": "400",
            "borderRadius": "0px",
            "boxShadow": "none",
            "letterSpacing": "2%",
            "lineHeight": "19.6px",
            "display": "block",
            "position": "static"
          },
          {
            "tag": "a",
            "text": "Shop",
            "color": "lch(0 0 0)",
            "backgroundColor": "rgba(0, 0, 0, 0)",
            "fontFamily": "Grotesk, ui-sans-serif, system-ui, sans-serif, \"Apple Color Emoji\", \"Segoe UI Emoji\", \"Segoe UI Symbol\", \"Noto Color Emoji\"",
            "fontSize": "14px",
            "fontWeight": "400",
            "borderRadius": "0px",
            "boxShadow": "none",
            "letterSpacing": "2%",
            "lineHeight": "19.6px",
            "display": "inline",
            "position": "static"
          },
          {
            "tag": "p",
            "text": "Careers",
            "color": "lch(0 0 0)",
            "backgroundColor": "rgba(0, 0, 0, 0)",
            "fontFamily": "Grotesk, ui-sans-serif, system-ui, sans-serif, \"Apple Color Emoji\", \"Segoe UI Emoji\", \"Segoe UI Symbol\", \"Noto Color Emoji\"",
            "fontSize": "14px",
            "fontWeight": "400",
            "borderRadius": "0px",
            "boxShadow": "none",
            "letterSpacing": "2%",
            "lineHeight": "19.6px",
            "display": "block",
            "position": "static"
          },
          {
            "tag": "a",
            "text": "Careers",
            "color": "lch(0 0 0)",
            "backgroundColor": "rgba(0, 0, 0, 0)",
            "fontFamily": "Grotesk, ui-sans-serif, system-ui, sans-serif, \"Apple Color Emoji\", \"Segoe UI Emoji\", \"Segoe UI Symbol\", \"Noto Color Emoji\"",
            "fontSize": "14px",
            "fontWeight": "400",
            "borderRadius": "0px",
            "boxShadow": "none",
            "letterSpacing": "2%",
            "lineHeight": "19.6px",
            "display": "inline",
            "position": "static"
          },
          {
            "tag": "p",
            "text": "Press",
            "color": "lch(0 0 0)",
            "backgroundColor": "rgba(0, 0, 0, 0)",
            "fontFamily": "Grotesk, ui-sans-serif, system-ui, sans-serif, \"Apple Color Emoji\", \"Segoe UI Emoji\", \"Segoe UI Symbol\", \"Noto Color Emoji\"",
            "fontSize": "14px",
            "fontWeight": "400",
            "borderRadius": "0px",
            "boxShadow": "none",
            "letterSpacing": "2%",
            "lineHeight": "19.6px",
            "display": "block",
            "position": "static"
          },
          {
            "tag": "a",
            "text": "Press",
            "color": "lch(0 0 0)",
            "backgroundColor": "rgba(0, 0, 0, 0)",
            "fontFamily": "Grotesk, ui-sans-serif, system-ui, sans-serif, \"Apple Color Emoji\", \"Segoe UI Emoji\", \"Segoe UI Symbol\", \"Noto Color Emoji\"",
            "fontSize": "14px",
            "fontWeight": "400",
            "borderRadius": "0px",
            "boxShadow": "none",
            "letterSpacing": "2%",
            "lineHeight": "19.6px",
            "display": "inline",
            "position": "static"
          },
          {
            "tag": "p",
            "text": "Privacy Policy",
            "color": "lch(0 0 0)",
            "backgroundColor": "rgba(0, 0, 0, 0)",
            "fontFamily": "Grotesk, ui-sans-serif, system-ui, sans-serif, \"Apple Color Emoji\", \"Segoe UI Emoji\", \"Segoe UI Symbol\", \"Noto Color Emoji\"",
            "fontSize": "14px",
            "fontWeight": "400",
            "borderRadius": "0px",
            "boxShadow": "none",
            "letterSpacing": "2%",
            "lineHeight": "19.6px",
            "display": "block",
            "position": "static"
          },
          {
            "tag": "a",
            "text": "Privacy Policy",
            "color": "lch(0 0 0)",
            "backgroundColor": "rgba(0, 0, 0, 0)",
            "fontFamily": "Grotesk, ui-sans-serif, system-ui, sans-serif, \"Apple Color Emoji\", \"Segoe UI Emoji\", \"Segoe UI Symbol\", \"Noto Color Emoji\"",
            "fontSize": "14px",
            "fontWeight": "400",
            "borderRadius": "0px",
            "boxShadow": "none",
            "letterSpacing": "2%",
            "lineHeight": "19.6px",
            "display": "inline",
            "position": "static"
          },
          {
            "tag": "p",
            "text": "Cookie Policy",
            "color": "lch(0 0 0)",
            "backgroundColor": "rgba(0, 0, 0, 0)",
            "fontFamily": "Grotesk, ui-sans-serif, system-ui, sans-serif, \"Apple Color Emoji\", \"Segoe UI Emoji\", \"Segoe UI Symbol\", \"Noto Color Emoji\"",
            "fontSize": "14px",
            "fontWeight": "400",
            "borderRadius": "0px",
            "boxShadow": "none",
            "letterSpacing": "2%",
            "lineHeight": "19.6px",
            "display": "block",
            "position": "static"
          },
          {
            "tag": "a",
            "text": "Cookie Policy",
            "color": "lch(0 0 0)",
            "backgroundColor": "rgba(0, 0, 0, 0)",
            "fontFamily": "Grotesk, ui-sans-serif, system-ui, sans-serif, \"Apple Color Emoji\", \"Segoe UI Emoji\", \"Segoe UI Symbol\", \"Noto Color Emoji\"",
            "fontSize": "14px",
            "fontWeight": "400",
            "borderRadius": "0px",
            "boxShadow": "none",
            "letterSpacing": "2%",
            "lineHeight": "19.6px",
            "display": "inline",
            "position": "static"
          },
          {
            "tag": "p",
            "text": "Customer Feedback and Complaints Policy",
            "color": "lch(0 0 0)",
            "backgroundColor": "rgba(0, 0, 0, 0)",
            "fontFamily": "Grotesk, ui-sans-serif, system-ui, sans-serif, \"Apple Color Emoji\", \"Segoe UI Emoji\", \"Segoe UI Symbol\", \"Noto Color Emoji\"",
            "fontSize": "14px",
            "fontWeight": "400",
            "borderRadius": "0px",
            "boxShadow": "none",
            "letterSpacing": "2%",
            "lineHeight": "19.6px",
            "display": "block",
            "position": "static"
          },
          {
            "tag": "a",
            "text": "Customer Feedback and Complaints Policy",
            "color": "lch(0 0 0)",
            "backgroundColor": "rgba(0, 0, 0, 0)",
            "fontFamily": "Grotesk, ui-sans-serif, system-ui, sans-serif, \"Apple Color Emoji\", \"Segoe UI Emoji\", \"Segoe UI Symbol\", \"Noto Color Emoji\"",
            "fontSize": "14px",
            "fontWeight": "400",
            "borderRadius": "0px",
            "boxShadow": "none",
            "letterSpacing": "2%",
            "lineHeight": "19.6px",
            "display": "inline",
            "position": "static"
          },
          {
            "tag": "h3",
            "text": "Onsite",
            "color": "lch(0 0 0)",
            "backgroundColor": "rgba(0, 0, 0, 0)",
            "fontFamily": "Grotesk, ui-sans-serif, system-ui, sans-serif, \"Apple Color Emoji\", \"Segoe UI Emoji\", \"Segoe UI Symbol\", \"Noto Color Emoji\"",
            "fontSize": "14px",
            "fontWeight": "400",
            "borderRadius": "0px",
            "boxShadow": "none",
            "letterSpacing": "2%",
            "lineHeight": "19.6px",
            "display": "block",
            "position": "static"
          },
          {
            "tag": "p",
            "text": "Whats On",
            "color": "lch(0 0 0)",
            "backgroundColor": "rgba(0, 0, 0, 0)",
            "fontFamily": "Grotesk, ui-sans-serif, system-ui, sans-serif, \"Apple Color Emoji\", \"Segoe UI Emoji\", \"Segoe UI Symbol\", \"Noto Color Emoji\"",
            "fontSize": "14px",
            "fontWeight": "400",
            "borderRadius": "0px",
            "boxShadow": "none",
            "letterSpacing": "2%",
            "lineHeight": "19.6px",
            "display": "block",
            "position": "static"
          },
          {
            "tag": "a",
            "text": "Whats On",
            "color": "lch(0 0 0)",
            "backgroundColor": "rgba(0, 0, 0, 0)",
            "fontFamily": "Grotesk, ui-sans-serif, system-ui, sans-serif, \"Apple Color Emoji\", \"Segoe UI Emoji\", \"Segoe UI Symbol\", \"Noto Color Emoji\"",
            "fontSize": "14px",
            "fontWeight": "400",
            "borderRadius": "0px",
            "boxShadow": "none",
            "letterSpacing": "2%",
            "lineHeight": "19.6px",
            "display": "inline",
            "position": "static"
          },
          {
            "tag": "p",
            "text": "Food and Drink",
            "color": "lch(0 0 0)",
            "backgroundColor": "rgba(0, 0, 0, 0)",
            "fontFamily": "Grotesk, ui-sans-serif, system-ui, sans-serif, \"Apple Color Emoji\", \"Segoe UI Emoji\", \"Segoe UI Symbol\", \"Noto Color Emoji\"",
            "fontSize": "14px",
            "fontWeight": "400",
            "borderRadius": "0px",
            "boxShadow": "none",
            "letterSpacing": "2%",
            "lineHeight": "19.6px",
            "display": "block",
            "position": "static"
          },
          {
            "tag": "a",
            "text": "Food and Drink",
            "color": "lch(0 0 0)",
            "backgroundColor": "rgba(0, 0, 0, 0)",
            "fontFamily": "Grotesk, ui-sans-serif, system-ui, sans-serif, \"Apple Color Emoji\", \"Segoe UI Emoji\", \"Segoe UI Symbol\", \"Noto Color Emoji\"",
            "fontSize": "14px",
            "fontWeight": "400",
            "borderRadius": "0px",
            "boxShadow": "none",
            "letterSpacing": "2%",
            "lineHeight": "19.6px",
            "display": "inline",
            "position": "static"
          },
          {
            "tag": "p",
            "text": "FAQs",
            "color": "lch(0 0 0)",
            "backgroundColor": "rgba(0, 0, 0, 0)",
            "fontFamily": "Grotesk, ui-sans-serif, system-ui, sans-serif, \"Apple Color Emoji\", \"Segoe UI Emoji\", \"Segoe UI Symbol\", \"Noto Color Emoji\"",
            "fontSize": "14px",
            "fontWeight": "400",
            "borderRadius": "0px",
            "boxShadow": "none",
            "letterSpacing": "2%",
            "lineHeight": "19.6px",
            "display": "block",
            "position": "static"
          },
          {
            "tag": "a",
            "text": "FAQs",
            "color": "lch(0 0 0)",
            "backgroundColor": "rgba(0, 0, 0, 0)",
            "fontFamily": "Grotesk, ui-sans-serif, system-ui, sans-serif, \"Apple Color Emoji\", \"Segoe UI Emoji\", \"Segoe UI Symbol\", \"Noto Color Emoji\"",
            "fontSize": "14px",
            "fontWeight": "400",
            "borderRadius": "0px",
            "boxShadow": "none",
            "letterSpacing": "2%",
            "lineHeight": "19.6px",
            "display": "inline",
            "position": "static"
          },
          {
            "tag": "p",
            "text": "Travel Guidance",
            "color": "lch(0 0 0)",
            "backgroundColor": "rgba(0, 0, 0, 0)",
            "fontFamily": "Grotesk, ui-sans-serif, system-ui, sans-serif, \"Apple Color Emoji\", \"Segoe UI Emoji\", \"Segoe UI Symbol\", \"Noto Color Emoji\"",
            "fontSize": "14px",
            "fontWeight": "400",
            "borderRadius": "0px",
            "boxShadow": "none",
            "letterSpacing": "2%",
            "lineHeight": "19.6px",
            "display": "block",
            "position": "static"
          },
          {
            "tag": "a",
            "text": "Travel Guidance",
            "color": "lch(0 0 0)",
            "backgroundColor": "rgba(0, 0, 0, 0)",
            "fontFamily": "Grotesk, ui-sans-serif, system-ui, sans-serif, \"Apple Color Emoji\", \"Segoe UI Emoji\", \"Segoe UI Symbol\", \"Noto Color Emoji\"",
            "fontSize": "14px",
            "fontWeight": "400",
            "borderRadius": "0px",
            "boxShadow": "none",
            "letterSpacing": "2%",
            "lineHeight": "19.6px",
            "display": "inline",
            "position": "static"
          },
          {
            "tag": "p",
            "text": "Accessibility",
            "color": "lch(0 0 0)",
            "backgroundColor": "rgba(0, 0, 0, 0)",
            "fontFamily": "Grotesk, ui-sans-serif, system-ui, sans-serif, \"Apple Color Emoji\", \"Segoe UI Emoji\", \"Segoe UI Symbol\", \"Noto Color Emoji\"",
            "fontSize": "14px",
            "fontWeight": "400",
            "borderRadius": "0px",
            "boxShadow": "none",
            "letterSpacing": "2%",
            "lineHeight": "19.6px",
            "display": "block",
            "position": "static"
          },
          {
            "tag": "a",
            "text": "Accessibility",
            "color": "lch(0 0 0)",
            "backgroundColor": "rgba(0, 0, 0, 0)",
            "fontFamily": "Grotesk, ui-sans-serif, system-ui, sans-serif, \"Apple Color Emoji\", \"Segoe UI Emoji\", \"Segoe UI Symbol\", \"Noto Color Emoji\"",
            "fontSize": "14px",
            "fontWeight": "400",
            "borderRadius": "0px",
            "boxShadow": "none",
            "letterSpacing": "2%",
            "lineHeight": "19.6px",
            "display": "inline",
            "position": "static"
          },
          {
            "tag": "h3",
            "text": "Socials",
            "color": "lch(0 0 0)",
            "backgroundColor": "rgba(0, 0, 0, 0)",
            "fontFamily": "Grotesk, ui-sans-serif, system-ui, sans-serif, \"Apple Color Emoji\", \"Segoe UI Emoji\", \"Segoe UI Symbol\", \"Noto Color Emoji\"",
            "fontSize": "14px",
            "fontWeight": "400",
            "borderRadius": "0px",
            "boxShadow": "none",
            "letterSpacing": "2%",
            "lineHeight": "19.6px",
            "display": "block",
            "position": "static"
          },
          {
            "tag": "p",
            "text": "Instagram",
            "color": "lch(0 0 0)",
            "backgroundColor": "rgba(0, 0, 0, 0)",
            "fontFamily": "Grotesk, ui-sans-serif, system-ui, sans-serif, \"Apple Color Emoji\", \"Segoe UI Emoji\", \"Segoe UI Symbol\", \"Noto Color Emoji\"",
            "fontSize": "14px",
            "fontWeight": "400",
            "borderRadius": "0px",
            "boxShadow": "none",
            "letterSpacing": "2%",
            "lineHeight": "19.6px",
            "display": "block",
            "position": "static"
          },
          {
            "tag": "a",
            "text": "Instagram",
            "color": "lch(0 0 0)",
            "backgroundColor": "rgba(0, 0, 0, 0)",
            "fontFamily": "Grotesk, ui-sans-serif, system-ui, sans-serif, \"Apple Color Emoji\", \"Segoe UI Emoji\", \"Segoe UI Symbol\", \"Noto Color Emoji\"",
            "fontSize": "14px",
            "fontWeight": "400",
            "borderRadius": "0px",
            "boxShadow": "none",
            "letterSpacing": "2%",
            "lineHeight": "19.6px",
            "display": "inline",
            "position": "static"
          },
          {
            "tag": "p",
            "text": "Facebook",
            "color": "lch(0 0 0)",
            "backgroundColor": "rgba(0, 0, 0, 0)",
            "fontFamily": "Grotesk, ui-sans-serif, system-ui, sans-serif, \"Apple Color Emoji\", \"Segoe UI Emoji\", \"Segoe UI Symbol\", \"Noto Color Emoji\"",
            "fontSize": "14px",
            "fontWeight": "400",
            "borderRadius": "0px",
            "boxShadow": "none",
            "letterSpacing": "2%",
            "lineHeight": "19.6px",
            "display": "block",
            "position": "static"
          },
          {
            "tag": "a",
            "text": "Facebook",
            "color": "lch(0 0 0)",
            "backgroundColor": "rgba(0, 0, 0, 0)",
            "fontFamily": "Grotesk, ui-sans-serif, system-ui, sans-serif, \"Apple Color Emoji\", \"Segoe UI Emoji\", \"Segoe UI Symbol\", \"Noto Color Emoji\"",
            "fontSize": "14px",
            "fontWeight": "400",
            "borderRadius": "0px",
            "boxShadow": "none",
            "letterSpacing": "2%",
            "lineHeight": "19.6px",
            "display": "inline",
            "position": "static"
          },
          {
            "tag": "p",
            "text": "Tiktok",
            "color": "lch(0 0 0)",
            "backgroundColor": "rgba(0, 0, 0, 0)",
            "fontFamily": "Grotesk, ui-sans-serif, system-ui, sans-serif, \"Apple Color Emoji\", \"Segoe UI Emoji\", \"Segoe UI Symbol\", \"Noto Color Emoji\"",
            "fontSize": "14px",
            "fontWeight": "400",
            "borderRadius": "0px",
            "boxShadow": "none",
            "letterSpacing": "2%",
            "lineHeight": "19.6px",
            "display": "block",
            "position": "static"
          },
          {
            "tag": "a",
            "text": "Tiktok",
            "color": "lch(0 0 0)",
            "backgroundColor": "rgba(0, 0, 0, 0)",
            "fontFamily": "Grotesk, ui-sans-serif, system-ui, sans-serif, \"Apple Color Emoji\", \"Segoe UI Emoji\", \"Segoe UI Symbol\", \"Noto Color Emoji\"",
            "fontSize": "14px",
            "fontWeight": "400",
            "borderRadius": "0px",
            "boxShadow": "none",
            "letterSpacing": "2%",
            "lineHeight": "19.6px",
            "display": "inline",
            "position": "static"
          },
          {
            "tag": "p",
            "text": "Youtube",
            "color": "lch(0 0 0)",
            "backgroundColor": "rgba(0, 0, 0, 0)",
            "fontFamily": "Grotesk, ui-sans-serif, system-ui, sans-serif, \"Apple Color Emoji\", \"Segoe UI Emoji\", \"Segoe UI Symbol\", \"Noto Color Emoji\"",
            "fontSize": "14px",
            "fontWeight": "400",
            "borderRadius": "0px",
            "boxShadow": "none",
            "letterSpacing": "2%",
            "lineHeight": "19.6px",
            "display": "block",
            "position": "static"
          },
          {
            "tag": "a",
            "text": "Youtube",
            "color": "lch(0 0 0)",
            "backgroundColor": "rgba(0, 0, 0, 0)",
            "fontFamily": "Grotesk, ui-sans-serif, system-ui, sans-serif, \"Apple Color Emoji\", \"Segoe UI Emoji\", \"Segoe UI Symbol\", \"Noto Color Emoji\"",
            "fontSize": "14px",
            "fontWeight": "400",
            "borderRadius": "0px",
            "boxShadow": "none",
            "letterSpacing": "2%",
            "lineHeight": "19.6px",
            "display": "inline",
            "position": "static"
          },
          {
            "tag": "p",
            "text": "X",
            "color": "lch(0 0 0)",
            "backgroundColor": "rgba(0, 0, 0, 0)",
            "fontFamily": "Grotesk, ui-sans-serif, system-ui, sans-serif, \"Apple Color Emoji\", \"Segoe UI Emoji\", \"Segoe UI Symbol\", \"Noto Color Emoji\"",
            "fontSize": "14px",
            "fontWeight": "400",
            "borderRadius": "0px",
            "boxShadow": "none",
            "letterSpacing": "2%",
            "lineHeight": "19.6px",
            "display": "block",
            "position": "static"
          },
          {
            "tag": "a",
            "text": "X",
            "color": "lch(0 0 0)",
            "backgroundColor": "rgba(0, 0, 0, 0)",
            "fontFamily": "Grotesk, ui-sans-serif, system-ui, sans-serif, \"Apple Color Emoji\", \"Segoe UI Emoji\", \"Segoe UI Symbol\", \"Noto Color Emoji\"",
            "fontSize": "14px",
            "fontWeight": "400",
            "borderRadius": "0px",
            "boxShadow": "none",
            "letterSpacing": "2%",
            "lineHeight": "19.6px",
            "display": "inline",
            "position": "static"
          },
          {
            "tag": "p",
            "text": "Sign up to our monthly newsletter:",
            "color": "rgb(0, 0, 0)",
            "backgroundColor": "rgba(0, 0, 0, 0)",
            "fontFamily": "Grotesk, ui-sans-serif, system-ui, sans-serif, \"Apple Color Emoji\", \"Segoe UI Emoji\", \"Segoe UI Symbol\", \"Noto Color Emoji\"",
            "fontSize": "14px",
            "fontWeight": "400",
            "borderRadius": "0px",
            "boxShadow": "none",
            "letterSpacing": "2%",
            "lineHeight": "19.6px",
            "display": "block",
            "position": "static"
          },
          {
            "tag": "a",
            "text": "Sign Up",
            "color": "rgb(255, 255, 255)",
            "backgroundColor": "rgb(0, 43, 255)",
            "fontFamily": "Grotesk, ui-sans-serif, system-ui, sans-serif, \"Apple Color Emoji\", \"Segoe UI Emoji\", \"Segoe UI Symbol\", \"Noto Color Emoji\"",
            "fontSize": "14px",
            "fontWeight": "400",
            "borderRadius": "28px",
            "boxShadow": "none",
            "letterSpacing": "2%",
            "lineHeight": "19.6px",
            "display": "flex",
            "position": "static"
          },
          {
            "tag": "p",
            "text": "Registered Charity No. 1063640",
            "color": "lch(0 0 0)",
            "backgroundColor": "rgba(0, 0, 0, 0)",
            "fontFamily": "Grotesk, ui-sans-serif, system-ui, sans-serif, \"Apple Color Emoji\", \"Segoe UI Emoji\", \"Segoe UI Symbol\", \"Noto Color Emoji\"",
            "fontSize": "14px",
            "fontWeight": "400",
            "borderRadius": "0px",
            "boxShadow": "none",
            "letterSpacing": "2%",
            "lineHeight": "19.6px",
            "display": "block",
            "position": "static"
          },
          {
            "tag": "button",
            "text": "Feedback",
            "color": "rgb(253, 253, 254)",
            "backgroundColor": "rgb(50, 79, 190)",
            "fontFamily": "Arial, sans-serif, Tahoma",
            "fontSize": "16px",
            "fontWeight": "400",
            "borderRadius": "6px 6px 0px 0px",
            "boxShadow": "none",
            "letterSpacing": "normal",
            "lineHeight": "normal",
            "display": "flex",
            "position": "absolute"
          },
          {
            "tag": "h2",
            "text": "How would you rate your experience on our website?",
            "color": "rgb(1, 1, 2)",
            "backgroundColor": "rgb(255, 255, 255)",
            "fontFamily": "Roboto, Arial, sans-serif",
            "fontSize": "16px",
            "fontWeight": "500",
            "borderRadius": "0px",
            "boxShadow": "none",
            "letterSpacing": "normal",
            "lineHeight": "24px",
            "display": "block",
            "position": "static"
          },
          {
            "tag": "button",
            "text": "Next",
            "color": "rgb(172, 176, 190)",
            "backgroundColor": "rgb(240, 241, 243)",
            "fontFamily": "Roboto, Arial, sans-serif",
            "fontSize": "14px",
            "fontWeight": "500",
            "borderRadius": "4px",
            "boxShadow": "none",
            "letterSpacing": "normal",
            "lineHeight": "20px",
            "display": "block",
            "position": "static"
          },
          {
            "tag": "button",
            "text": "Skip",
            "color": "rgb(1, 1, 2)",
            "backgroundColor": "rgba(0, 0, 0, 0)",
            "fontFamily": "Roboto, Arial, sans-serif",
            "fontSize": "14px",
            "fontWeight": "400",
            "borderRadius": "0px",
            "boxShadow": "none",
            "letterSpacing": "normal",
            "lineHeight": "normal",
            "display": "block",
            "position": "static"
          }
        ],
        "colors": [
          {
            "hex": "#f5f5f5",
            "count": 24856
          },
          {
            "hex": "#a9a9a9",
            "count": 464
          },
          {
            "hex": "#5c5c5c",
            "count": 101
          },
          {
            "hex": "#2f4dbc",
            "count": 55
          },
          {
            "hex": "#2c2c2c",
            "count": 42
          },
          {
            "hex": "#5670d2",
            "count": 34
          },
          {
            "hex": "#0429f9",
            "count": 26
          },
          {
            "hex": "#3656eb",
            "count": 22
          }
        ],
        "screenshotPalette": [
          {
            "hex": "#f5f5f5",
            "count": 24856
          },
          {
            "hex": "#a9a9a9",
            "count": 464
          },
          {
            "hex": "#5c5c5c",
            "count": 101
          },
          {
            "hex": "#2f4dbc",
            "count": 55
          },
          {
            "hex": "#2c2c2c",
            "count": 42
          },
          {
            "hex": "#5670d2",
            "count": 34
          },
          {
            "hex": "#0429f9",
            "count": 26
          },
          {
            "hex": "#3656eb",
            "count": 22
          }
        ]
      },
      "screenshot": "screenshots/desktop.jpg"
    },
    "mobile": {
      "ok": true,
      "analysis": {
        "mode": "mobile",
        "title": "Somerset House | 404",
        "url": "https://www.somersethouse.org.uk/blog/decentralise",
        "body": {
          "backgroundColor": "rgba(0, 0, 0, 0)",
          "color": "rgb(0, 0, 0)",
          "fontFamily": "Grotesk, ui-sans-serif, system-ui, sans-serif, \"Apple Color Emoji\", \"Segoe UI Emoji\", \"Segoe UI Symbol\", \"Noto Color Emoji\"",
          "fontSize": "16px",
          "lineHeight": "24px"
        },
        "heading": {
          "tag": "h1",
          "text": "404",
          "color": "rgb(0, 0, 0)",
          "backgroundColor": "rgba(0, 0, 0, 0)",
          "fontFamily": "Grotesk, ui-sans-serif, system-ui, sans-serif, \"Apple Color Emoji\", \"Segoe UI Emoji\", \"Segoe UI Symbol\", \"Noto Color Emoji\"",
          "fontSize": "30px",
          "fontWeight": "400",
          "borderRadius": "0px",
          "boxShadow": "none",
          "letterSpacing": "2%",
          "lineHeight": "42px",
          "display": "block",
          "position": "static"
        },
        "bodyText": {
          "tag": "p",
          "text": "Page not found.",
          "color": "rgb(0, 0, 0)",
          "backgroundColor": "rgba(0, 0, 0, 0)",
          "fontFamily": "Grotesk, ui-sans-serif, system-ui, sans-serif, \"Apple Color Emoji\", \"Segoe UI Emoji\", \"Segoe UI Symbol\", \"Noto Color Emoji\"",
          "fontSize": "14px",
          "fontWeight": "400",
          "borderRadius": "0px",
          "boxShadow": "none",
          "letterSpacing": "2%",
          "lineHeight": "19.6px",
          "display": "block",
          "position": "static"
        },
        "button": {
          "tag": "button",
          "text": "Menu",
          "color": "rgb(0, 0, 0)",
          "backgroundColor": "rgb(238, 238, 238)",
          "fontFamily": "Grotesk, ui-sans-serif, system-ui, sans-serif, \"Apple Color Emoji\", \"Segoe UI Emoji\", \"Segoe UI Symbol\", \"Noto Color Emoji\"",
          "fontSize": "14px",
          "fontWeight": "400",
          "borderRadius": "28px",
          "boxShadow": "none",
          "letterSpacing": "2%",
          "lineHeight": "14px",
          "display": "flex",
          "position": "static"
        },
        "link": {
          "tag": "a",
          "text": "Skip to main content",
          "color": "rgb(0, 0, 0)",
          "backgroundColor": "rgb(255, 255, 255)",
          "fontFamily": "Grotesk, ui-sans-serif, system-ui, sans-serif, \"Apple Color Emoji\", \"Segoe UI Emoji\", \"Segoe UI Symbol\", \"Noto Color Emoji\"",
          "fontSize": "16px",
          "fontWeight": "400",
          "borderRadius": "0px",
          "boxShadow": "none",
          "letterSpacing": "normal",
          "lineHeight": "24px",
          "display": "block",
          "position": "absolute"
        },
        "sticky": true,
        "fonts": [
          {
            "family": "Grotesk",
            "style": "normal",
            "weight": "400",
            "status": "loaded"
          },
          {
            "family": "Roman",
            "style": "normal",
            "weight": "400",
            "status": "unloaded"
          },
          {
            "family": "hotjar",
            "style": "normal",
            "weight": "normal",
            "status": "unloaded"
          },
          {
            "family": "roboto",
            "style": "normal",
            "weight": "400",
            "status": "loaded"
          },
          {
            "family": "roboto",
            "style": "normal",
            "weight": "500",
            "status": "loaded"
          }
        ],
        "sample": [
          {
            "tag": "body",
            "text": "Skip to main contentSkip to primary navigationSkip to secondary navigationMenuMenuCloseHomeWhat's OnExhibitionsEventsOnl",
            "color": "rgb(0, 0, 0)",
            "backgroundColor": "rgba(0, 0, 0, 0)",
            "fontFamily": "Grotesk, ui-sans-serif, system-ui, sans-serif, \"Apple Color Emoji\", \"Segoe UI Emoji\", \"Segoe UI Symbol\", \"Noto Color Emoji\"",
            "fontSize": "16px",
            "fontWeight": "400",
            "borderRadius": "0px",
            "boxShadow": "none",
            "letterSpacing": "normal",
            "lineHeight": "24px",
            "display": "block",
            "position": "static"
          },
          {
            "tag": "a",
            "text": "Skip to main content",
            "color": "rgb(0, 0, 0)",
            "backgroundColor": "rgb(255, 255, 255)",
            "fontFamily": "Grotesk, ui-sans-serif, system-ui, sans-serif, \"Apple Color Emoji\", \"Segoe UI Emoji\", \"Segoe UI Symbol\", \"Noto Color Emoji\"",
            "fontSize": "16px",
            "fontWeight": "400",
            "borderRadius": "0px",
            "boxShadow": "none",
            "letterSpacing": "normal",
            "lineHeight": "24px",
            "display": "block",
            "position": "absolute"
          },
          {
            "tag": "a",
            "text": "Skip to primary navigation",
            "color": "rgb(0, 0, 0)",
            "backgroundColor": "rgb(255, 255, 255)",
            "fontFamily": "Grotesk, ui-sans-serif, system-ui, sans-serif, \"Apple Color Emoji\", \"Segoe UI Emoji\", \"Segoe UI Symbol\", \"Noto Color Emoji\"",
            "fontSize": "16px",
            "fontWeight": "400",
            "borderRadius": "0px",
            "boxShadow": "none",
            "letterSpacing": "normal",
            "lineHeight": "24px",
            "display": "block",
            "position": "absolute"
          },
          {
            "tag": "a",
            "text": "Skip to secondary navigation",
            "color": "rgb(0, 0, 0)",
            "backgroundColor": "rgb(255, 255, 255)",
            "fontFamily": "Grotesk, ui-sans-serif, system-ui, sans-serif, \"Apple Color Emoji\", \"Segoe UI Emoji\", \"Segoe UI Symbol\", \"Noto Color Emoji\"",
            "fontSize": "16px",
            "fontWeight": "400",
            "borderRadius": "0px",
            "boxShadow": "none",
            "letterSpacing": "normal",
            "lineHeight": "24px",
            "display": "block",
            "position": "absolute"
          },
          {
            "tag": "a",
            "text": "",
            "color": "rgb(0, 0, 0)",
            "backgroundColor": "rgba(0, 0, 0, 0)",
            "fontFamily": "Grotesk, ui-sans-serif, system-ui, sans-serif, \"Apple Color Emoji\", \"Segoe UI Emoji\", \"Segoe UI Symbol\", \"Noto Color Emoji\"",
            "fontSize": "16px",
            "fontWeight": "400",
            "borderRadius": "0px",
            "boxShadow": "none",
            "letterSpacing": "normal",
            "lineHeight": "24px",
            "display": "inline",
            "position": "static"
          },
          {
            "tag": "nav",
            "text": "MenuMenuCloseHomeWhat's OnExhibitionsEventsOnline CommissionsSomerset House StudiosArtistsResidencies and OpportunitiesC",
            "color": "rgb(0, 0, 0)",
            "backgroundColor": "rgba(0, 0, 0, 0)",
            "fontFamily": "Grotesk, ui-sans-serif, system-ui, sans-serif, \"Apple Color Emoji\", \"Segoe UI Emoji\", \"Segoe UI Symbol\", \"Noto Color Emoji\"",
            "fontSize": "16px",
            "fontWeight": "400",
            "borderRadius": "0px",
            "boxShadow": "none",
            "letterSpacing": "normal",
            "lineHeight": "24px",
            "display": "block",
            "position": "static"
          },
          {
            "tag": "button",
            "text": "Menu",
            "color": "rgb(0, 0, 0)",
            "backgroundColor": "rgb(238, 238, 238)",
            "fontFamily": "Grotesk, ui-sans-serif, system-ui, sans-serif, \"Apple Color Emoji\", \"Segoe UI Emoji\", \"Segoe UI Symbol\", \"Noto Color Emoji\"",
            "fontSize": "14px",
            "fontWeight": "400",
            "borderRadius": "28px",
            "boxShadow": "none",
            "letterSpacing": "2%",
            "lineHeight": "14px",
            "display": "flex",
            "position": "static"
          },
          {
            "tag": "button",
            "text": "Search",
            "color": "rgb(0, 0, 0)",
            "backgroundColor": "rgb(238, 238, 238)",
            "fontFamily": "Grotesk, ui-sans-serif, system-ui, sans-serif, \"Apple Color Emoji\", \"Segoe UI Emoji\", \"Segoe UI Symbol\", \"Noto Color Emoji\"",
            "fontSize": "14px",
            "fontWeight": "400",
            "borderRadius": "9999px",
            "boxShadow": "none",
            "letterSpacing": "2%",
            "lineHeight": "14px",
            "display": "flex",
            "position": "static"
          },
          {
            "tag": "main",
            "text": "404Page not found.Home of Cultural InnovatorsOpening HoursStrand entrance8am—11pmThe Courtauld Gallery10am—6pmNew Wing8a",
            "color": "rgb(0, 0, 0)",
            "backgroundColor": "rgba(0, 0, 0, 0)",
            "fontFamily": "Grotesk, ui-sans-serif, system-ui, sans-serif, \"Apple Color Emoji\", \"Segoe UI Emoji\", \"Segoe UI Symbol\", \"Noto Color Emoji\"",
            "fontSize": "16px",
            "fontWeight": "400",
            "borderRadius": "0px",
            "boxShadow": "none",
            "letterSpacing": "normal",
            "lineHeight": "24px",
            "display": "block",
            "position": "static"
          },
          {
            "tag": "header",
            "text": "404Page not found.",
            "color": "rgb(0, 0, 0)",
            "backgroundColor": "rgb(255, 255, 255)",
            "fontFamily": "Grotesk, ui-sans-serif, system-ui, sans-serif, \"Apple Color Emoji\", \"Segoe UI Emoji\", \"Segoe UI Symbol\", \"Noto Color Emoji\"",
            "fontSize": "16px",
            "fontWeight": "400",
            "borderRadius": "7px",
            "boxShadow": "none",
            "letterSpacing": "normal",
            "lineHeight": "24px",
            "display": "block",
            "position": "static"
          },
          {
            "tag": "h1",
            "text": "404",
            "color": "rgb(0, 0, 0)",
            "backgroundColor": "rgba(0, 0, 0, 0)",
            "fontFamily": "Grotesk, ui-sans-serif, system-ui, sans-serif, \"Apple Color Emoji\", \"Segoe UI Emoji\", \"Segoe UI Symbol\", \"Noto Color Emoji\"",
            "fontSize": "30px",
            "fontWeight": "400",
            "borderRadius": "0px",
            "boxShadow": "none",
            "letterSpacing": "2%",
            "lineHeight": "42px",
            "display": "block",
            "position": "static"
          },
          {
            "tag": "p",
            "text": "Page not found.",
            "color": "rgb(0, 0, 0)",
            "backgroundColor": "rgba(0, 0, 0, 0)",
            "fontFamily": "Grotesk, ui-sans-serif, system-ui, sans-serif, \"Apple Color Emoji\", \"Segoe UI Emoji\", \"Segoe UI Symbol\", \"Noto Color Emoji\"",
            "fontSize": "14px",
            "fontWeight": "400",
            "borderRadius": "0px",
            "boxShadow": "none",
            "letterSpacing": "2%",
            "lineHeight": "19.6px",
            "display": "block",
            "position": "static"
          },
          {
            "tag": "footer",
            "text": "Home of Cultural InnovatorsOpening HoursStrand entrance8am—11pmThe Courtauld Gallery10am—6pmNew Wing8am—11pmAboutAbout U",
            "color": "lch(0 0 0)",
            "backgroundColor": "rgb(255, 255, 255)",
            "fontFamily": "Grotesk, ui-sans-serif, system-ui, sans-serif, \"Apple Color Emoji\", \"Segoe UI Emoji\", \"Segoe UI Symbol\", \"Noto Color Emoji\"",
            "fontSize": "16px",
            "fontWeight": "400",
            "borderRadius": "0px",
            "boxShadow": "none",
            "letterSpacing": "normal",
            "lineHeight": "24px",
            "display": "block",
            "position": "static"
          },
          {
            "tag": "h3",
            "text": "Home of Cultural Innovators",
            "color": "lch(0 0 0)",
            "backgroundColor": "rgba(0, 0, 0, 0)",
            "fontFamily": "Grotesk, ui-sans-serif, system-ui, sans-serif, \"Apple Color Emoji\", \"Segoe UI Emoji\", \"Segoe UI Symbol\", \"Noto Color Emoji\"",
            "fontSize": "30px",
            "fontWeight": "400",
            "borderRadius": "0px",
            "boxShadow": "none",
            "letterSpacing": "2%",
            "lineHeight": "42px",
            "display": "block",
            "position": "static"
          },
          {
            "tag": "h3",
            "text": "Opening Hours",
            "color": "lch(0 0 0)",
            "backgroundColor": "rgba(0, 0, 0, 0)",
            "fontFamily": "Grotesk, ui-sans-serif, system-ui, sans-serif, \"Apple Color Emoji\", \"Segoe UI Emoji\", \"Segoe UI Symbol\", \"Noto Color Emoji\"",
            "fontSize": "14px",
            "fontWeight": "400",
            "borderRadius": "0px",
            "boxShadow": "none",
            "letterSpacing": "2%",
            "lineHeight": "19.6px",
            "display": "block",
            "position": "static"
          },
          {
            "tag": "button",
            "text": "About",
            "color": "lch(0 0 0)",
            "backgroundColor": "rgba(0, 0, 0, 0)",
            "fontFamily": "Grotesk, ui-sans-serif, system-ui, sans-serif, \"Apple Color Emoji\", \"Segoe UI Emoji\", \"Segoe UI Symbol\", \"Noto Color Emoji\"",
            "fontSize": "16px",
            "fontWeight": "400",
            "borderRadius": "0px",
            "boxShadow": "none",
            "letterSpacing": "normal",
            "lineHeight": "24px",
            "display": "inline-block",
            "position": "static"
          },
          {
            "tag": "h3",
            "text": "About",
            "color": "lch(0 0 0)",
            "backgroundColor": "rgba(0, 0, 0, 0)",
            "fontFamily": "Grotesk, ui-sans-serif, system-ui, sans-serif, \"Apple Color Emoji\", \"Segoe UI Emoji\", \"Segoe UI Symbol\", \"Noto Color Emoji\"",
            "fontSize": "14px",
            "fontWeight": "400",
            "borderRadius": "0px",
            "boxShadow": "none",
            "letterSpacing": "2%",
            "lineHeight": "19.6px",
            "display": "block",
            "position": "static"
          },
          {
            "tag": "button",
            "text": "Onsite",
            "color": "lch(0 0 0)",
            "backgroundColor": "rgba(0, 0, 0, 0)",
            "fontFamily": "Grotesk, ui-sans-serif, system-ui, sans-serif, \"Apple Color Emoji\", \"Segoe UI Emoji\", \"Segoe UI Symbol\", \"Noto Color Emoji\"",
            "fontSize": "16px",
            "fontWeight": "400",
            "borderRadius": "0px",
            "boxShadow": "none",
            "letterSpacing": "normal",
            "lineHeight": "24px",
            "display": "inline-block",
            "position": "static"
          },
          {
            "tag": "h3",
            "text": "Onsite",
            "color": "lch(0 0 0)",
            "backgroundColor": "rgba(0, 0, 0, 0)",
            "fontFamily": "Grotesk, ui-sans-serif, system-ui, sans-serif, \"Apple Color Emoji\", \"Segoe UI Emoji\", \"Segoe UI Symbol\", \"Noto Color Emoji\"",
            "fontSize": "14px",
            "fontWeight": "400",
            "borderRadius": "0px",
            "boxShadow": "none",
            "letterSpacing": "2%",
            "lineHeight": "19.6px",
            "display": "block",
            "position": "static"
          },
          {
            "tag": "button",
            "text": "Socials",
            "color": "lch(0 0 0)",
            "backgroundColor": "rgba(0, 0, 0, 0)",
            "fontFamily": "Grotesk, ui-sans-serif, system-ui, sans-serif, \"Apple Color Emoji\", \"Segoe UI Emoji\", \"Segoe UI Symbol\", \"Noto Color Emoji\"",
            "fontSize": "16px",
            "fontWeight": "400",
            "borderRadius": "0px",
            "boxShadow": "none",
            "letterSpacing": "normal",
            "lineHeight": "24px",
            "display": "inline-block",
            "position": "static"
          },
          {
            "tag": "h3",
            "text": "Socials",
            "color": "lch(0 0 0)",
            "backgroundColor": "rgba(0, 0, 0, 0)",
            "fontFamily": "Grotesk, ui-sans-serif, system-ui, sans-serif, \"Apple Color Emoji\", \"Segoe UI Emoji\", \"Segoe UI Symbol\", \"Noto Color Emoji\"",
            "fontSize": "14px",
            "fontWeight": "400",
            "borderRadius": "0px",
            "boxShadow": "none",
            "letterSpacing": "2%",
            "lineHeight": "19.6px",
            "display": "block",
            "position": "static"
          },
          {
            "tag": "p",
            "text": "Registered Charity No. 1063640",
            "color": "lch(0 0 0)",
            "backgroundColor": "rgba(0, 0, 0, 0)",
            "fontFamily": "Grotesk, ui-sans-serif, system-ui, sans-serif, \"Apple Color Emoji\", \"Segoe UI Emoji\", \"Segoe UI Symbol\", \"Noto Color Emoji\"",
            "fontSize": "14px",
            "fontWeight": "400",
            "borderRadius": "0px",
            "boxShadow": "none",
            "letterSpacing": "2%",
            "lineHeight": "19.6px",
            "display": "block",
            "position": "static"
          },
          {
            "tag": "button",
            "text": "Feedback",
            "color": "rgb(253, 253, 254)",
            "backgroundColor": "rgb(50, 79, 190)",
            "fontFamily": "Arial, sans-serif, Tahoma",
            "fontSize": "16px",
            "fontWeight": "400",
            "borderRadius": "6px 6px 0px 0px",
            "boxShadow": "none",
            "letterSpacing": "normal",
            "lineHeight": "normal",
            "display": "flex",
            "position": "fixed"
          },
          {
            "tag": "button",
            "text": "",
            "color": "rgb(0, 0, 0)",
            "backgroundColor": "rgba(0, 0, 0, 0)",
            "fontFamily": "Roboto, Arial, sans-serif",
            "fontSize": "16px",
            "fontWeight": "400",
            "borderRadius": "0px",
            "boxShadow": "none",
            "letterSpacing": "normal",
            "lineHeight": "normal",
            "display": "flex",
            "position": "static"
          },
          {
            "tag": "h2",
            "text": "How would you rate your experience on our website?",
            "color": "rgb(1, 1, 2)",
            "backgroundColor": "rgb(255, 255, 255)",
            "fontFamily": "Roboto, Arial, sans-serif",
            "fontSize": "16px",
            "fontWeight": "500",
            "borderRadius": "0px",
            "boxShadow": "none",
            "letterSpacing": "normal",
            "lineHeight": "24px",
            "display": "block",
            "position": "static"
          },
          {
            "tag": "button",
            "text": "Next",
            "color": "rgb(172, 176, 190)",
            "backgroundColor": "rgb(240, 241, 243)",
            "fontFamily": "Roboto, Arial, sans-serif",
            "fontSize": "14px",
            "fontWeight": "500",
            "borderRadius": "4px",
            "boxShadow": "none",
            "letterSpacing": "normal",
            "lineHeight": "20px",
            "display": "block",
            "position": "static"
          },
          {
            "tag": "button",
            "text": "Skip",
            "color": "rgb(1, 1, 2)",
            "backgroundColor": "rgba(0, 0, 0, 0)",
            "fontFamily": "Roboto, Arial, sans-serif",
            "fontSize": "14px",
            "fontWeight": "500",
            "borderRadius": "4px",
            "boxShadow": "none",
            "letterSpacing": "normal",
            "lineHeight": "20px",
            "display": "block",
            "position": "static"
          }
        ],
        "colors": [
          {
            "hex": "#fbfbfb",
            "count": 23900
          },
          {
            "hex": "#a4a4a4",
            "count": 631
          },
          {
            "hex": "#2f4dbc",
            "count": 361
          },
          {
            "hex": "#1a1a1a",
            "count": 288
          },
          {
            "hex": "#626262",
            "count": 273
          },
          {
            "hex": "#99a7da",
            "count": 84
          },
          {
            "hex": "#5069c4",
            "count": 45
          },
          {
            "hex": "#7588cf",
            "count": 18
          }
        ],
        "screenshotPalette": [
          {
            "hex": "#fbfbfb",
            "count": 23900
          },
          {
            "hex": "#a4a4a4",
            "count": 631
          },
          {
            "hex": "#2f4dbc",
            "count": 361
          },
          {
            "hex": "#1a1a1a",
            "count": 288
          },
          {
            "hex": "#626262",
            "count": 273
          },
          {
            "hex": "#99a7da",
            "count": 84
          },
          {
            "hex": "#5069c4",
            "count": 45
          },
          {
            "hex": "#7588cf",
            "count": 18
          }
        ]
      },
      "screenshot": "screenshots/mobile.jpg"
    }
  }
}
