{
  "slug": "bruno-simon",
  "title": "Bruno Simon",
  "liveUrl": "https://bruno-simon.com/",
  "domain": "bruno-simon.com",
  "loadmoreUrl": "https://bruno-simon.com/",
  "sourceLabel": "manual curation",
  "sourceUrl": "https://bruno-simon.com/",
  "description": "A 3D portfolio that turns navigation into play. It is useful design fuel because the interface is inseparable from motion, physics, and personality.",
  "credits": "Bruno Simon",
  "added": "Manual seed",
  "tags": [
    "3d-space",
    "playful",
    "portfolio"
  ],
  "captureChecklist": {
    "loadmoreMetadataParsed": true,
    "desktopVisited": true,
    "mobileVisited": true,
    "desktopScreenshotSaved": true,
    "mobileScreenshotSaved": true,
    "fontsExtracted": true,
    "colorPaletteExtracted": true
  },
  "capture": {
    "status": "ok",
    "capturedAt": "2026-04-06T20:34:31.991Z",
    "desktop": {
      "ok": true,
      "analysis": {
        "mode": "desktop",
        "title": "Bruno's",
        "url": "https://bruno-simon.com/",
        "body": {
          "backgroundColor": "rgba(0, 0, 0, 0)",
          "color": "rgb(0, 0, 0)",
          "fontFamily": "Nunito, sans-serif",
          "fontSize": "20px",
          "lineHeight": "normal"
        },
        "bodyText": {
          "tag": "body",
          "text": "Interact\n                Unstuck\n                \n                \n                \n                \n            \n      ",
          "color": "rgb(0, 0, 0)",
          "backgroundColor": "rgba(0, 0, 0, 0)",
          "fontFamily": "Nunito, sans-serif",
          "fontSize": "20px",
          "fontWeight": "400",
          "borderRadius": "0px",
          "boxShadow": "none",
          "letterSpacing": "normal",
          "lineHeight": "normal",
          "display": "block",
          "position": "fixed"
        },
        "button": {
          "tag": "button",
          "text": "",
          "color": "rgb(0, 0, 0)",
          "backgroundColor": "rgba(0, 0, 0, 0)",
          "fontFamily": "Nunito, sans-serif",
          "fontSize": "20px",
          "fontWeight": "400",
          "borderRadius": "0px",
          "boxShadow": "none",
          "letterSpacing": "normal",
          "lineHeight": "normal",
          "display": "block",
          "position": "absolute"
        },
        "sticky": true,
        "fonts": [
          {
            "family": "Amatic SC",
            "style": "normal",
            "weight": "700",
            "status": "unloaded"
          },
          {
            "family": "Amatic SC",
            "style": "normal",
            "weight": "700",
            "status": "unloaded"
          },
          {
            "family": "Amatic SC",
            "style": "normal",
            "weight": "700",
            "status": "unloaded"
          },
          {
            "family": "Amatic SC",
            "style": "normal",
            "weight": "700",
            "status": "unloaded"
          },
          {
            "family": "Amatic SC",
            "style": "normal",
            "weight": "700",
            "status": "loaded"
          },
          {
            "family": "Nunito",
            "style": "normal",
            "weight": "400",
            "status": "unloaded"
          },
          {
            "family": "Nunito",
            "style": "normal",
            "weight": "400",
            "status": "unloaded"
          },
          {
            "family": "Nunito",
            "style": "normal",
            "weight": "400",
            "status": "unloaded"
          },
          {
            "family": "Nunito",
            "style": "normal",
            "weight": "400",
            "status": "unloaded"
          },
          {
            "family": "Nunito",
            "style": "normal",
            "weight": "400",
            "status": "loaded"
          },
          {
            "family": "Nunito",
            "style": "normal",
            "weight": "700",
            "status": "unloaded"
          },
          {
            "family": "Nunito",
            "style": "normal",
            "weight": "700",
            "status": "unloaded"
          },
          {
            "family": "Nunito",
            "style": "normal",
            "weight": "700",
            "status": "unloaded"
          },
          {
            "family": "Nunito",
            "style": "normal",
            "weight": "700",
            "status": "unloaded"
          },
          {
            "family": "Nunito",
            "style": "normal",
            "weight": "700",
            "status": "loaded"
          },
          {
            "family": "Nunito",
            "style": "normal",
            "weight": "900",
            "status": "unloaded"
          },
          {
            "family": "Nunito",
            "style": "normal",
            "weight": "900",
            "status": "unloaded"
          },
          {
            "family": "Nunito",
            "style": "normal",
            "weight": "900",
            "status": "unloaded"
          },
          {
            "family": "Nunito",
            "style": "normal",
            "weight": "900",
            "status": "unloaded"
          },
          {
            "family": "Nunito",
            "style": "normal",
            "weight": "900",
            "status": "unloaded"
          },
          {
            "family": "Pally-Regular",
            "style": "normal",
            "weight": "400",
            "status": "unloaded"
          },
          {
            "family": "Pally-Medium",
            "style": "normal",
            "weight": "500",
            "status": "loaded"
          },
          {
            "family": "Pally-Bold",
            "style": "normal",
            "weight": "700",
            "status": "unloaded"
          }
        ],
        "sample": [
          {
            "tag": "body",
            "text": "Interact\n                Unstuck\n                \n                \n                \n                \n            \n      ",
            "color": "rgb(0, 0, 0)",
            "backgroundColor": "rgba(0, 0, 0, 0)",
            "fontFamily": "Nunito, sans-serif",
            "fontSize": "20px",
            "fontWeight": "400",
            "borderRadius": "0px",
            "boxShadow": "none",
            "letterSpacing": "normal",
            "lineHeight": "normal",
            "display": "block",
            "position": "fixed"
          },
          {
            "tag": "button",
            "text": "",
            "color": "rgb(0, 0, 0)",
            "backgroundColor": "rgba(0, 0, 0, 0)",
            "fontFamily": "Nunito, sans-serif",
            "fontSize": "20px",
            "fontWeight": "400",
            "borderRadius": "0px",
            "boxShadow": "none",
            "letterSpacing": "normal",
            "lineHeight": "normal",
            "display": "block",
            "position": "absolute"
          },
          {
            "tag": "div",
            "text": "",
            "color": "rgb(0, 0, 0)",
            "backgroundColor": "rgba(0, 0, 0, 0)",
            "fontFamily": "Nunito, sans-serif",
            "fontSize": "20px",
            "fontWeight": "400",
            "borderRadius": "0px",
            "boxShadow": "none",
            "letterSpacing": "normal",
            "lineHeight": "normal",
            "display": "block",
            "position": "absolute"
          },
          {
            "tag": "button",
            "text": "",
            "color": "rgb(0, 0, 0)",
            "backgroundColor": "rgba(0, 0, 0, 0)",
            "fontFamily": "Nunito, sans-serif",
            "fontSize": "20px",
            "fontWeight": "400",
            "borderRadius": "0px",
            "boxShadow": "none",
            "letterSpacing": "normal",
            "lineHeight": "normal",
            "display": "block",
            "position": "absolute"
          },
          {
            "tag": "div",
            "text": "",
            "color": "rgb(0, 0, 0)",
            "backgroundColor": "rgba(0, 0, 0, 0)",
            "fontFamily": "Nunito, sans-serif",
            "fontSize": "20px",
            "fontWeight": "400",
            "borderRadius": "0px",
            "boxShadow": "none",
            "letterSpacing": "normal",
            "lineHeight": "normal",
            "display": "block",
            "position": "absolute"
          }
        ],
        "colors": [
          {
            "hex": "#1e0f4a",
            "count": 15723
          },
          {
            "hex": "#19063d",
            "count": 8199
          },
          {
            "hex": "#472a71",
            "count": 543
          },
          {
            "hex": "#221295",
            "count": 503
          },
          {
            "hex": "#58348d",
            "count": 263
          },
          {
            "hex": "#724aa6",
            "count": 140
          },
          {
            "hex": "#cdb1ea",
            "count": 115
          },
          {
            "hex": "#af90d4",
            "count": 114
          }
        ],
        "screenshotPalette": [
          {
            "hex": "#1e0f4a",
            "count": 15723
          },
          {
            "hex": "#19063d",
            "count": 8199
          },
          {
            "hex": "#472a71",
            "count": 543
          },
          {
            "hex": "#221295",
            "count": 503
          },
          {
            "hex": "#58348d",
            "count": 263
          },
          {
            "hex": "#724aa6",
            "count": 140
          },
          {
            "hex": "#cdb1ea",
            "count": 115
          },
          {
            "hex": "#af90d4",
            "count": 114
          }
        ]
      },
      "screenshot": "screenshots/desktop.jpg"
    },
    "mobile": {
      "ok": true,
      "analysis": {
        "mode": "mobile",
        "title": "Bruno's",
        "url": "https://bruno-simon.com/",
        "body": {
          "backgroundColor": "rgba(0, 0, 0, 0)",
          "color": "rgb(0, 0, 0)",
          "fontFamily": "Nunito, sans-serif",
          "fontSize": "16px",
          "lineHeight": "normal"
        },
        "bodyText": {
          "tag": "body",
          "text": "Interact\n                Unstuck\n                \n                \n                \n                \n            \n      ",
          "color": "rgb(0, 0, 0)",
          "backgroundColor": "rgba(0, 0, 0, 0)",
          "fontFamily": "Nunito, sans-serif",
          "fontSize": "16px",
          "fontWeight": "400",
          "borderRadius": "0px",
          "boxShadow": "none",
          "letterSpacing": "normal",
          "lineHeight": "normal",
          "display": "block",
          "position": "fixed"
        },
        "button": {
          "tag": "button",
          "text": "",
          "color": "rgb(0, 0, 0)",
          "backgroundColor": "rgba(0, 0, 0, 0)",
          "fontFamily": "Nunito, sans-serif",
          "fontSize": "16px",
          "fontWeight": "400",
          "borderRadius": "0px",
          "boxShadow": "none",
          "letterSpacing": "normal",
          "lineHeight": "normal",
          "display": "block",
          "position": "absolute"
        },
        "sticky": true,
        "fonts": [
          {
            "family": "Amatic SC",
            "style": "normal",
            "weight": "700",
            "status": "unloaded"
          },
          {
            "family": "Amatic SC",
            "style": "normal",
            "weight": "700",
            "status": "unloaded"
          },
          {
            "family": "Amatic SC",
            "style": "normal",
            "weight": "700",
            "status": "unloaded"
          },
          {
            "family": "Amatic SC",
            "style": "normal",
            "weight": "700",
            "status": "unloaded"
          },
          {
            "family": "Amatic SC",
            "style": "normal",
            "weight": "700",
            "status": "loaded"
          },
          {
            "family": "Nunito",
            "style": "normal",
            "weight": "400",
            "status": "unloaded"
          },
          {
            "family": "Nunito",
            "style": "normal",
            "weight": "400",
            "status": "unloaded"
          },
          {
            "family": "Nunito",
            "style": "normal",
            "weight": "400",
            "status": "unloaded"
          },
          {
            "family": "Nunito",
            "style": "normal",
            "weight": "400",
            "status": "unloaded"
          },
          {
            "family": "Nunito",
            "style": "normal",
            "weight": "400",
            "status": "loaded"
          },
          {
            "family": "Nunito",
            "style": "normal",
            "weight": "700",
            "status": "unloaded"
          },
          {
            "family": "Nunito",
            "style": "normal",
            "weight": "700",
            "status": "unloaded"
          },
          {
            "family": "Nunito",
            "style": "normal",
            "weight": "700",
            "status": "unloaded"
          },
          {
            "family": "Nunito",
            "style": "normal",
            "weight": "700",
            "status": "unloaded"
          },
          {
            "family": "Nunito",
            "style": "normal",
            "weight": "700",
            "status": "loaded"
          },
          {
            "family": "Nunito",
            "style": "normal",
            "weight": "900",
            "status": "unloaded"
          },
          {
            "family": "Nunito",
            "style": "normal",
            "weight": "900",
            "status": "unloaded"
          },
          {
            "family": "Nunito",
            "style": "normal",
            "weight": "900",
            "status": "unloaded"
          },
          {
            "family": "Nunito",
            "style": "normal",
            "weight": "900",
            "status": "unloaded"
          },
          {
            "family": "Nunito",
            "style": "normal",
            "weight": "900",
            "status": "unloaded"
          },
          {
            "family": "Pally-Regular",
            "style": "normal",
            "weight": "400",
            "status": "unloaded"
          },
          {
            "family": "Pally-Medium",
            "style": "normal",
            "weight": "500",
            "status": "loaded"
          },
          {
            "family": "Pally-Bold",
            "style": "normal",
            "weight": "700",
            "status": "unloaded"
          }
        ],
        "sample": [
          {
            "tag": "body",
            "text": "Interact\n                Unstuck\n                \n                \n                \n                \n            \n      ",
            "color": "rgb(0, 0, 0)",
            "backgroundColor": "rgba(0, 0, 0, 0)",
            "fontFamily": "Nunito, sans-serif",
            "fontSize": "16px",
            "fontWeight": "400",
            "borderRadius": "0px",
            "boxShadow": "none",
            "letterSpacing": "normal",
            "lineHeight": "normal",
            "display": "block",
            "position": "fixed"
          },
          {
            "tag": "button",
            "text": "",
            "color": "rgb(0, 0, 0)",
            "backgroundColor": "rgba(0, 0, 0, 0)",
            "fontFamily": "Nunito, sans-serif",
            "fontSize": "16px",
            "fontWeight": "400",
            "borderRadius": "0px",
            "boxShadow": "none",
            "letterSpacing": "normal",
            "lineHeight": "normal",
            "display": "block",
            "position": "absolute"
          },
          {
            "tag": "div",
            "text": "",
            "color": "rgb(0, 0, 0)",
            "backgroundColor": "rgba(0, 0, 0, 0)",
            "fontFamily": "Nunito, sans-serif",
            "fontSize": "16px",
            "fontWeight": "400",
            "borderRadius": "0px",
            "boxShadow": "none",
            "letterSpacing": "normal",
            "lineHeight": "normal",
            "display": "block",
            "position": "absolute"
          },
          {
            "tag": "button",
            "text": "",
            "color": "rgb(0, 0, 0)",
            "backgroundColor": "rgba(0, 0, 0, 0)",
            "fontFamily": "Nunito, sans-serif",
            "fontSize": "16px",
            "fontWeight": "400",
            "borderRadius": "0px",
            "boxShadow": "none",
            "letterSpacing": "normal",
            "lineHeight": "normal",
            "display": "block",
            "position": "absolute"
          },
          {
            "tag": "div",
            "text": "",
            "color": "rgb(0, 0, 0)",
            "backgroundColor": "rgba(0, 0, 0, 0)",
            "fontFamily": "Nunito, sans-serif",
            "fontSize": "16px",
            "fontWeight": "400",
            "borderRadius": "0px",
            "boxShadow": "none",
            "letterSpacing": "normal",
            "lineHeight": "normal",
            "display": "block",
            "position": "absolute"
          }
        ],
        "colors": [
          {
            "hex": "#2a0e3b",
            "count": 10215
          },
          {
            "hex": "#4f1e57",
            "count": 6570
          },
          {
            "hex": "#351b56",
            "count": 4555
          },
          {
            "hex": "#87529d",
            "count": 1126
          },
          {
            "hex": "#47173d",
            "count": 1004
          },
          {
            "hex": "#692e95",
            "count": 1000
          },
          {
            "hex": "#9652dc",
            "count": 838
          },
          {
            "hex": "#684866",
            "count": 292
          }
        ],
        "screenshotPalette": [
          {
            "hex": "#2a0e3b",
            "count": 10215
          },
          {
            "hex": "#4f1e57",
            "count": 6570
          },
          {
            "hex": "#351b56",
            "count": 4555
          },
          {
            "hex": "#87529d",
            "count": 1126
          },
          {
            "hex": "#47173d",
            "count": 1004
          },
          {
            "hex": "#692e95",
            "count": 1000
          },
          {
            "hex": "#9652dc",
            "count": 838
          },
          {
            "hex": "#684866",
            "count": 292
          }
        ]
      },
      "screenshot": "screenshots/mobile.jpg"
    }
  }
}
